rpdb/__init__.py
rpdb/breakinfo.py
rpdb/breakpoint.py
rpdb/compat.py
rpdb/const.py
rpdb/crypto.py
rpdb/debugee.py
rpdb/events.py
rpdb/exceptions.py
rpdb/firewall_test.py
rpdb/globals.py
rpdb/repr.py
rpdb/rpc.py
rpdb/session_manager.py
rpdb/source_provider.py
rpdb/state_manager.py
rpdb/utils.py
rpdb2.py
rpdb2-2.0.0.1.2.dist-info/WHEEL
rpdb2-2.0.0.1.2.dist-info/entry_points.txt
rpdb2-2.0.0.1.2.dist-info/LICENSE.txt
rpdb2-2.0.0.1.2.dist-info/METADATA
rpdb2-2.0.0.1.2.dist-info/RECORD
