Metadata-Version: 2.1
Name: rpdb2
Version: 2.0.0.1.2
Summary: rpdb2 module extracted from winpdb pacage.
License: GNU GPL
Author: Philippe Fremy, Nir Aides
Requires-Python: >=3.4,<4.0
Classifier: License :: Other/Proprietary License
Classifier: Programming Language :: Python :: 3
Classifier: Programming Language :: Python :: 3.4
Classifier: Programming Language :: Python :: 3.5
Classifier: Programming Language :: Python :: 3.6
Classifier: Programming Language :: Python :: 3.7
Classifier: Programming Language :: Python :: 3.8
Classifier: Programming Language :: Python :: 3.9
Classifier: Programming Language :: Python :: 3.10
Classifier: Programming Language :: Python :: 3.11
